{
	"info": {
		"_postman_id": "89b48bac-7e31-4ca3-befb-4cc7638aa949",
		"name": "PROYECTO - TRANSPORTE",
		"schema": "https://schema.getpostman.com/json/collection/v2.1.0/collection.json",
		"_exporter_id": "39400177",
		"_collection_link": "https://proyecto-transporte.postman.co/workspace/Proyecto---Transporte-Workspace~dbd70176-8779-486c-b5a8-afb2102285a5/collection/39400249-89b48bac-7e31-4ca3-befb-4cc7638aa949?action=share&source=collection_link&creator=39400177"
	},
	"item": [
		{
			"name": "REGISTRO PROGRAMACION",
			"item": [
				{
					"name": "EMPLEADO NO EXISTE",
					"request": {
						"method": "POST",
						"header": [],
						"body": {
							"mode": "raw",
							"raw": "{\r\n    \"idEmpleado\": 100\r\n}",
							"options": {
								"raw": {
									"language": "json"
								}
							}
						},
						"url": {
							"raw": "http://localhost:8080/programar/ruta",
							"protocol": "http",
							"host": [
								"localhost"
							],
							"port": "8080",
							"path": [
								"programar",
								"ruta"
							]
						}
					},
					"response": []
				},
				{
					"name": "CARRO NO EXISTE",
					"request": {
						"method": "POST",
						"header": [],
						"body": {
							"mode": "raw",
							"raw": "{\r\n    \"idEmpleado\": 2,\r\n    \"idCarro\": 100\r\n}",
							"options": {
								"raw": {
									"language": "json"
								}
							}
						},
						"url": {
							"raw": "http://localhost:8080/programar/ruta",
							"protocol": "http",
							"host": [
								"localhost"
							],
							"port": "8080",
							"path": [
								"programar",
								"ruta"
							]
						}
					},
					"response": []
				},
				{
					"name": "CARRO NO DISPONIBLE",
					"request": {
						"method": "POST",
						"header": [],
						"body": {
							"mode": "raw",
							"raw": "{\r\n    \"idEmpleado\": 2,\r\n    \"idCarro\": 4\r\n}",
							"options": {
								"raw": {
									"language": "json"
								}
							}
						},
						"url": {
							"raw": "http://localhost:8080/programar/ruta",
							"protocol": "http",
							"host": [
								"localhost"
							],
							"port": "8080",
							"path": [
								"programar",
								"ruta"
							]
						}
					},
					"response": []
				},
				{
					"name": "CONDUCTOR NO EXISTE",
					"request": {
						"method": "POST",
						"header": [],
						"body": {
							"mode": "raw",
							"raw": "{\r\n    \"idEmpleado\": 2,\r\n    \"idCarro\": 1,\r\n    \"idConductor\": 100\r\n}",
							"options": {
								"raw": {
									"language": "json"
								}
							}
						},
						"url": {
							"raw": "http://localhost:8080/programar/ruta",
							"protocol": "http",
							"host": [
								"localhost"
							],
							"port": "8080",
							"path": [
								"programar",
								"ruta"
							]
						}
					},
					"response": []
				},
				{
					"name": "CONDUCTOR NO DISPONIBLE",
					"request": {
						"method": "POST",
						"header": [],
						"body": {
							"mode": "raw",
							"raw": "{\r\n    \"idEmpleado\": 2,\r\n    \"idCarro\": 1,\r\n    \"idConductor\": 2\r\n}",
							"options": {
								"raw": {
									"language": "json"
								}
							}
						},
						"url": {
							"raw": "http://localhost:8080/programar/ruta",
							"protocol": "http",
							"host": [
								"localhost"
							],
							"port": "8080",
							"path": [
								"programar",
								"ruta"
							]
						}
					},
					"response": []
				},
				{
					"name": "RUTA NO EXISTE",
					"request": {
						"method": "POST",
						"header": [],
						"body": {
							"mode": "raw",
							"raw": "{\r\n    \"idEmpleado\": 2,\r\n    \"idCarro\": 1,\r\n    \"idConductor\": 1,\r\n    \"idRuta\": 7\r\n}",
							"options": {
								"raw": {
									"language": "json"
								}
							}
						},
						"url": {
							"raw": "http://localhost:8080/programar/ruta",
							"protocol": "http",
							"host": [
								"localhost"
							],
							"port": "8080",
							"path": [
								"programar",
								"ruta"
							]
						}
					},
					"response": []
				},
				{
					"name": "FECHA ASIG. NO VALIDA",
					"request": {
						"method": "POST",
						"header": [],
						"body": {
							"mode": "raw",
							"raw": "{\r\n    \"idEmpleado\": 2,\r\n    \"idCarro\": 1,\r\n    \"idConductor\": 1,\r\n    \"idRuta\": 2,\r\n    \"fechaAsignacion\": \"13/01/2024\"\r\n}",
							"options": {
								"raw": {
									"language": "json"
								}
							}
						},
						"url": {
							"raw": "http://localhost:8080/programar/ruta",
							"protocol": "http",
							"host": [
								"localhost"
							],
							"port": "8080",
							"path": [
								"programar",
								"ruta"
							]
						}
					},
					"response": []
				},
				{
					"name": "FECHA FIN NO VALIDA",
					"request": {
						"method": "POST",
						"header": [],
						"body": {
							"mode": "raw",
							"raw": "{\r\n    \"idEmpleado\": 2,\r\n    \"idCarro\": 1,\r\n    \"idConductor\": 1,\r\n    \"idRuta\": 2,\r\n    \"fechaAsignacion\": \"21/01/2024\",\r\n    \"fechaFinProgramada\": \"20/01/2024\"\r\n}",
							"options": {
								"raw": {
									"language": "json"
								}
							}
						},
						"url": {
							"raw": "http://localhost:8080/programar/ruta",
							"protocol": "http",
							"host": [
								"localhost"
							],
							"port": "8080",
							"path": [
								"programar",
								"ruta"
							]
						}
					},
					"response": []
				},
				{
					"name": "PROGRAMACION NO EXITOSA",
					"request": {
						"method": "POST",
						"header": [],
						"body": {
							"mode": "raw",
							"raw": "{\r\n    \"idEmpleado\": 2,\r\n    \"idCarro\": 1,\r\n    \"idConductor\": 1,\r\n    \"idRuta\": 2,\r\n    \"fechaAsignacion\": \"20/01/2024\",\r\n    \"fechaFinProgramada\": \"23/01/2024\"\r\n}",
							"options": {
								"raw": {
									"language": "json"
								}
							}
						},
						"url": {
							"raw": "http://localhost:8080/programar/ruta",
							"protocol": "http",
							"host": [
								"localhost"
							],
							"port": "8080",
							"path": [
								"programar",
								"ruta"
							]
						}
					},
					"response": []
				}
			]
		},
		{
			"name": "REGISTRAR CONDUCTOR",
			"item": [
				{
					"name": "DNI CON UNA LETRA",
					"request": {
						"method": "POST",
						"header": [],
						"body": {
							"mode": "raw",
							"raw": "{\r\n    \"nombre\": \"Genaro\",\r\n    \"apellido\": \"Flores\",\r\n    \"dni\": \"1892p021\"\r\n}",
							"options": {
								"raw": {
									"language": "json"
								}
							}
						},
						"url": {
							"raw": "http://localhost:8080/conductor",
							"protocol": "http",
							"host": [
								"localhost"
							],
							"port": "8080",
							"path": [
								"conductor"
							]
						}
					},
					"response": []
				},
				{
					"name": "DNI MENOR A 8 DIGITOS",
					"request": {
						"method": "POST",
						"header": [],
						"body": {
							"mode": "raw",
							"raw": "{\r\n    \"nombre\": \"Genaro\",\r\n    \"apellido\": \"Flores\",\r\n    \"dni\": \"8922021\"\r\n}",
							"options": {
								"raw": {
									"language": "json"
								}
							}
						},
						"url": {
							"raw": "http://localhost:8080/conductor",
							"protocol": "http",
							"host": [
								"localhost"
							],
							"port": "8080",
							"path": [
								"conductor"
							]
						}
					},
					"response": []
				},
				{
					"name": "TELEFONO CON UNA LETRA",
					"request": {
						"method": "POST",
						"header": [],
						"body": {
							"mode": "raw",
							"raw": "{\r\n    \"nombre\": \"Genaro\",\r\n    \"apellido\": \"Flores\",\r\n    \"dni\": \"18928021\",\r\n    \"correo\": \"gflores@gmail.com\",\r\n    \"telefono\": \"90783k990\"\r\n}",
							"options": {
								"raw": {
									"language": "json"
								}
							}
						},
						"url": {
							"raw": "http://localhost:8080/conductor",
							"protocol": "http",
							"host": [
								"localhost"
							],
							"port": "8080",
							"path": [
								"conductor"
							]
						}
					},
					"response": []
				},
				{
					"name": "TELEFONO MENOR A 9 DIGITOS",
					"request": {
						"method": "POST",
						"header": [],
						"body": {
							"mode": "raw",
							"raw": "{\r\n    \"nombre\": \"Genaro\",\r\n    \"apellido\": \"Flores\",\r\n    \"dni\": \"18928021\",\r\n    \"correo\": \"gflores@gmail.com\",\r\n    \"telefono\": \"90783490\"\r\n}",
							"options": {
								"raw": {
									"language": "json"
								}
							}
						},
						"url": {
							"raw": "http://localhost:8080/conductor",
							"protocol": "http",
							"host": [
								"localhost"
							],
							"port": "8080",
							"path": [
								"conductor"
							]
						}
					},
					"response": []
				},
				{
					"name": "TELEFONO EMPIEZA DIFERENTE DE 9",
					"request": {
						"method": "POST",
						"header": [],
						"body": {
							"mode": "raw",
							"raw": "{\r\n    \"nombre\": \"Genaro\",\r\n    \"apellido\": \"Flores\",\r\n    \"dni\": \"18928021\",\r\n    \"correo\": \"gflores@gmail.com\",\r\n    \"telefono\": \"807834990\"\r\n}",
							"options": {
								"raw": {
									"language": "json"
								}
							}
						},
						"url": {
							"raw": "http://localhost:8080/conductor",
							"protocol": "http",
							"host": [
								"localhost"
							],
							"port": "8080",
							"path": [
								"conductor"
							]
						}
					},
					"response": []
				}
			]
		},
		{
			"name": "INCIDENTE CONDUCTOR",
			"item": [
				{
					"name": "CONDUCTOR INCIDENTE",
					"protocolProfileBehavior": {
						"disableBodyPruning": true
					},
					"request": {
						"method": "GET",
						"header": [],
						"body": {
							"mode": "raw",
							"raw": "",
							"options": {
								"raw": {
									"language": "json"
								}
							}
						},
						"url": {
							"raw": "http://localhost:8080/conductor/5/incidentes?fechaInicio=01/01/2023&fechaFinal=01/01/2023",
							"protocol": "http",
							"host": [
								"localhost"
							],
							"port": "8080",
							"path": [
								"conductor",
								"5",
								"incidentes"
							],
							"query": [
								{
									"key": "fechaInicio",
									"value": "01/01/2023"
								},
								{
									"key": "fechaFinal",
									"value": "01/01/2023"
								}
							]
						}
					},
					"response": []
				},
				{
					"name": "NO CONDUCTOR NO INCIDENTE",
					"request": {
						"method": "GET",
						"header": [],
						"url": {
							"raw": "http://localhost:8080/conductor/6/incidentes?fechaInicio=01/01/2023&fechaFinal=01/01/2023",
							"protocol": "http",
							"host": [
								"localhost"
							],
							"port": "8080",
							"path": [
								"conductor",
								"6",
								"incidentes"
							],
							"query": [
								{
									"key": "fechaInicio",
									"value": "01/01/2023"
								},
								{
									"key": "fechaFinal",
									"value": "01/01/2023"
								}
							]
						}
					},
					"response": []
				},
				{
					"name": "FECHAS INCORRECTAS",
					"request": {
						"method": "GET",
						"header": [],
						"url": {
							"raw": "http://localhost:8080/conductor/4/incidentes?fechaInicio=31/01/2023&fechaFinal=01/01/2023",
							"protocol": "http",
							"host": [
								"localhost"
							],
							"port": "8080",
							"path": [
								"conductor",
								"4",
								"incidentes"
							],
							"query": [
								{
									"key": "fechaInicio",
									"value": "31/01/2023"
								},
								{
									"key": "fechaFinal",
									"value": "01/01/2023"
								}
							]
						}
					},
					"response": []
				},
				{
					"name": "FORMATO FECHAS INVALIDAS",
					"request": {
						"method": "GET",
						"header": [],
						"url": {
							"raw": "http://localhost:8080/conductor/4/incidentes?fechaInicio=2023-01-31&fechaFinal=20230101",
							"protocol": "http",
							"host": [
								"localhost"
							],
							"port": "8080",
							"path": [
								"conductor",
								"4",
								"incidentes"
							],
							"query": [
								{
									"key": "fechaInicio",
									"value": "2023-01-31"
								},
								{
									"key": "fechaFinal",
									"value": "20230101"
								}
							]
						}
					},
					"response": []
				}
			]
		},
		{
			"name": "CANTIDAD DE INCIDENTES",
			"item": [
				{
					"name": "CANT DE INCIDENTES",
					"request": {
						"method": "GET",
						"header": [],
						"url": {
							"raw": "http://localhost:8080/frecuencia/incidente/1",
							"protocol": "http",
							"host": [
								"localhost"
							],
							"port": "8080",
							"path": [
								"frecuencia",
								"incidente",
								"1"
							]
						}
					},
					"response": []
				},
				{
					"name": "TIPO DE INCIDENTE INVALIDO",
					"request": {
						"method": "GET",
						"header": [],
						"url": {
							"raw": "http://localhost:8080/frecuencia/incidente/6",
							"protocol": "http",
							"host": [
								"localhost"
							],
							"port": "8080",
							"path": [
								"frecuencia",
								"incidente",
								"6"
							]
						}
					},
					"response": []
				}
			]
		},
		{
			"name": "REGISTRO TALLER",
			"item": [
				{
					"name": "DATOS OK",
					"request": {
						"method": "POST",
						"header": [],
						"body": {
							"mode": "raw",
							"raw": "{\r\n    \"nombre\" : \"Gonza\",\r\n    \"direccion\": \"av. Lima 276\",\r\n    \"telefono\" : 9884343\r\n}",
							"options": {
								"raw": {
									"language": "json"
								}
							}
						},
						"url": {
							"raw": "http://localhost:8080/api/talleres",
							"protocol": "http",
							"host": [
								"localhost"
							],
							"port": "8080",
							"path": [
								"api",
								"talleres"
							]
						}
					},
					"response": []
				},
				{
					"name": "TELEFONO INVALIDO",
					"request": {
						"method": "POST",
						"header": [],
						"body": {
							"mode": "raw",
							"raw": "{\r\n    \"nombre\" : \"Gonza\",\r\n    \"direccion\": \"av. Lima 276\",\r\n    \"telefono\" : \"988434a7\"\r\n}",
							"options": {
								"raw": {
									"language": "json"
								}
							}
						},
						"url": {
							"raw": "http://localhost:8080/api/talleres",
							"protocol": "http",
							"host": [
								"localhost"
							],
							"port": "8080",
							"path": [
								"api",
								"talleres"
							]
						}
					},
					"response": []
				}
			]
		},
		{
			"name": "RUTA",
			"item": [
				{
					"name": "validarRuta",
					"request": {
						"method": "POST",
						"header": [],
						"body": {
							"mode": "raw",
							"raw": "{\r\n    \"origen\":\"Ciudad D\",\r\n    \"destino\":\"Ciudad D\"\r\n\r\n}",
							"options": {
								"raw": {
									"language": "json"
								}
							}
						},
						"url": {
							"raw": "http://localhost:8080/api/ruta/registrar",
							"protocol": "http",
							"host": [
								"localhost"
							],
							"port": "8080",
							"path": [
								"api",
								"ruta",
								"registrar"
							]
						}
					},
					"response": []
				},
				{
					"name": "nombre",
					"request": {
						"method": "POST",
						"header": [],
						"body": {
							"mode": "raw",
							"raw": "{\r\n    \"nombre\": \"ruta 1\"\r\n}",
							"options": {
								"raw": {
									"language": "json"
								}
							}
						},
						"url": {
							"raw": "http://localhost:8080/api/ruta/registrar",
							"protocol": "http",
							"host": [
								"localhost"
							],
							"port": "8080",
							"path": [
								"api",
								"ruta",
								"registrar"
							]
						}
					},
					"response": []
				},
				{
					"name": "distancia",
					"request": {
						"method": "POST",
						"header": [],
						"body": {
							"mode": "raw",
							"raw": "{\r\n    \"origen\":\"Ciudad A\",\r\n    \"destino\":\"Ciudad D\",\r\n    \"distancia\" : -500.0\r\n}",
							"options": {
								"raw": {
									"language": "json"
								}
							}
						},
						"url": {
							"raw": "http://localhost:8080/api/ruta/registrar",
							"protocol": "http",
							"host": [
								"localhost"
							],
							"port": "8080",
							"path": [
								"api",
								"ruta",
								"registrar"
							]
						}
					},
					"response": []
				},
				{
					"name": "Registro",
					"request": {
						"method": "POST",
						"header": [],
						"body": {
							"mode": "raw",
							"raw": "{\r\n    \"nombre\":\"Ruta 6\",\r\n    \"origen\":\"Ciudad B\",\r\n    \"destino\":\"Ciudad D\",\r\n    \"distancia\" : 450.0\r\n}",
							"options": {
								"raw": {
									"language": "json"
								}
							}
						},
						"url": {
							"raw": "http://localhost:8080/api/ruta/registrar",
							"protocol": "http",
							"host": [
								"localhost"
							],
							"port": "8080",
							"path": [
								"api",
								"ruta",
								"registrar"
							]
						}
					},
					"response": []
				}
			]
		},
		{
			"name": "REPARACION",
			"item": [
				{
					"name": "validarIncidente",
					"request": {
						"method": "POST",
						"header": [],
						"body": {
							"mode": "raw",
							"raw": "{\r\n    \"idincidente\":8\r\n}",
							"options": {
								"raw": {
									"language": "json"
								}
							}
						},
						"url": {
							"raw": "http://localhost:8080/api/reparacion/registrar",
							"protocol": "http",
							"host": [
								"localhost"
							],
							"port": "8080",
							"path": [
								"api",
								"reparacion",
								"registrar"
							]
						}
					},
					"response": []
				},
				{
					"name": "validarEstadoAuto",
					"request": {
						"method": "POST",
						"header": [],
						"body": {
							"mode": "raw",
							"raw": "{\r\n    \"idincidente\":2\r\n}",
							"options": {
								"raw": {
									"language": "json"
								}
							}
						},
						"url": {
							"raw": "http://localhost:8080/api/reparacion/registrar",
							"protocol": "http",
							"host": [
								"localhost"
							],
							"port": "8080",
							"path": [
								"api",
								"reparacion",
								"registrar"
							]
						}
					},
					"response": []
				},
				{
					"name": "validarempleado",
					"request": {
						"method": "POST",
						"header": [],
						"body": {
							"mode": "raw",
							"raw": "{\r\n    \"idincidente\":6,\r\n    \"idempleado\":9\r\n    \r\n\r\n}",
							"options": {
								"raw": {
									"language": "json"
								}
							}
						},
						"url": {
							"raw": "http://localhost:8080/api/reparacion/registrar",
							"protocol": "http",
							"host": [
								"localhost"
							],
							"port": "8080",
							"path": [
								"api",
								"reparacion",
								"registrar"
							]
						}
					},
					"response": []
				},
				{
					"name": "validartaller",
					"request": {
						"method": "POST",
						"header": [],
						"body": {
							"mode": "raw",
							"raw": "{\r\n    \"idincidente\":6,\r\n    \"idempleado\":3,\r\n    \"idtaller\": 9\r\n\r\n}",
							"options": {
								"raw": {
									"language": "json"
								}
							}
						},
						"url": {
							"raw": "http://localhost:8080/api/reparacion/registrar",
							"protocol": "http",
							"host": [
								"localhost"
							],
							"port": "8080",
							"path": [
								"api",
								"reparacion",
								"registrar"
							]
						}
					},
					"response": []
				},
				{
					"name": "validarfechareparacion",
					"request": {
						"method": "POST",
						"header": [],
						"body": {
							"mode": "raw",
							"raw": "{\r\n    \"idincidente\":6,\r\n    \"idempleado\":3,\r\n    \"idtaller\": 3,\r\n    \"fechareparacion\":\"12/06/2024\"\r\n}",
							"options": {
								"raw": {
									"language": "json"
								}
							}
						},
						"url": {
							"raw": "http://localhost:8080/api/reparacion/registrar",
							"protocol": "http",
							"host": [
								"localhost"
							],
							"port": "8080",
							"path": [
								"api",
								"reparacion",
								"registrar"
							]
						}
					},
					"response": []
				},
				{
					"name": "Transaccion",
					"request": {
						"method": "POST",
						"header": [],
						"body": {
							"mode": "raw",
							"raw": "{\r\n    \"idempleado\":3,\r\n    \"idincidente\":6,\r\n    \"idtaller\": 3,\r\n    \"fechareparacion\":\"14/01/2024\",\r\n    \"calificacion\":4,\r\n    \"costo\":210.0,\r\n    \"detalle\":\"Puerta Reparada\"\r\n\r\n}",
							"options": {
								"raw": {
									"language": "json"
								}
							}
						},
						"url": {
							"raw": "http://localhost:8080/api/reparacion/registrar",
							"protocol": "http",
							"host": [
								"localhost"
							],
							"port": "8080",
							"path": [
								"api",
								"reparacion",
								"registrar"
							]
						}
					},
					"response": []
				}
			]
		},
		{
			"name": "INCIDENTES",
			"item": [
				{
					"name": "Insertar Incidente",
					"request": {
						"method": "POST",
						"header": [],
						"body": {
							"mode": "raw",
							"raw": "{\r\n    \"empleado\":3,\r\n    \"programacion\":1,\r\n    \"tipo_incidente\":3,\r\n    \"fecha\":\"10/06/2024\",\r\n    \"detalle\":\"Fallos en el motor de arranque\"\r\n}",
							"options": {
								"raw": {
									"language": "json"
								}
							}
						},
						"url": {
							"raw": "localhost:8080/transporte/incidente",
							"host": [
								"localhost"
							],
							"port": "8080",
							"path": [
								"transporte",
								"incidente"
							]
						}
					},
					"response": []
				},
				{
					"name": "Rutas con mas incidentes",
					"request": {
						"method": "GET",
						"header": [],
						"url": {
							"raw": "localhost:8080/rutas/mas-incidentes",
							"host": [
								"localhost"
							],
							"port": "8080",
							"path": [
								"rutas",
								"mas-incidentes"
							]
						}
					},
					"response": []
				}
			]
		},
		{
			"name": "REGISTRAR CARRO",
			"item": [
				{
					"name": "registrarCarro",
					"request": {
						"method": "POST",
						"header": [],
						"body": {
							"mode": "raw",
							"raw": "{\r\n    \"placa\": \"XYA987\",\r\n    \"prox_mant\": \"2024-12-10\"\r\n}",
							"options": {
								"raw": {
									"language": "json"
								}
							}
						},
						"url": {
							"raw": "http://localhost:8080/registrarcarro",
							"protocol": "http",
							"host": [
								"localhost"
							],
							"port": "8080",
							"path": [
								"registrarcarro"
							]
						}
					},
					"response": []
				},
				{
					"name": "registrarTaller",
					"request": {
						"method": "POST",
						"header": [],
						"body": {
							"mode": "raw",
							"raw": "{\r\n    \"nombreTaller\": \"Taller Central\",\r\n    \"direccion\": \"Av. Los Robles 123\",\r\n    \"telefono\": \"987654321\"\r\n}",
							"options": {
								"raw": {
									"language": "json"
								}
							}
						},
						"url": {
							"raw": "http://localhost:8080/api/talleres",
							"protocol": "http",
							"host": [
								"localhost"
							],
							"port": "8080",
							"path": [
								"api",
								"talleres"
							]
						}
					},
					"response": []
				},
				{
					"name": "registrarMantenimiento",
					"request": {
						"method": "POST",
						"header": [],
						"body": {
							"mode": "raw",
							"raw": "{\r\n    \"id_empleado\": 1,\r\n    \"id_taller\": 2,\r\n    \"id_carro\": 3,\r\n    \"calificacion\": 4.5,\r\n    \"fecha_inicio\": \"2024-11-20\",\r\n    \"fecha_salida_programada\": \"2024-11-25\",\r\n    \"costo\": 1200.50,\r\n    \"detalle\": \"Cambio de frenos y mantenimiento general\"\r\n}",
							"options": {
								"raw": {
									"language": "json"
								}
							}
						},
						"url": {
							"raw": "http://localhost:8080/api/mantenimiento/registro",
							"protocol": "http",
							"host": [
								"localhost"
							],
							"port": "8080",
							"path": [
								"api",
								"mantenimiento",
								"registro"
							]
						}
					},
					"response": []
				}
			]
		}
	]
}